README.md
setup.py
apprest_interface/__init__.py
apprest_interface/api.py
apprest_interface.egg-info/PKG-INFO
apprest_interface.egg-info/SOURCES.txt
apprest_interface.egg-info/dependency_links.txt
apprest_interface.egg-info/requires.txt
apprest_interface.egg-info/top_level.txt