Metadata-Version: 1.2
Name: apprest-interface
Version: 1.0.7.dev0
Summary: A simple Python package to facilitate interactions with APP's API
Home-page: https://github.com/jjorissen52/apprest_interface
Author: John-Paul Jorissen
Author-email: jjorissen52@gmail.com
License: Apache
Keywords: APP Python WebServices REST API
Platform: UNKNOWN
Classifier: Development Status :: 3 - Alpha
Classifier: Intended Audience :: Developers
Classifier: Programming Language :: Python :: 3.6
Classifier: Operating System :: Microsoft :: Windows :: Windows 10
Classifier: Operating System :: POSIX :: Linux
Classifier: Topic :: Office/Business
Classifier: License :: OSI Approved :: Apache Software License
Classifier: Programming Language :: Python :: 3.6
Requires-Python: >=3.6
